{"name":"Darth Vader", "height":"202", "mass":"136", "hair_color":"none", "skin_color":"white", "eye_color":"yellow", "birth_year":"42BBY", "gender":"male", "homeworld":"https://swapi.co/api/planets/1/", "films":["https://swapi.co/api/films/2/", "https://swapi.co/api/films/6/", "https://swapi.co/api/films/3/", "https://swapi.co/api/films/1/"], "species":["https://swapi.co/api/species/1/"], "vehicles":[], "starships":["https://swapi.co/api/starships/13/"],"relatives":["https://swapi.co/api/characters/1/","https://swapi.co/api/charcters/5/","https://swapi.co/api/charcters/6/","https://swapi.co/api/charcters/7/","https://swapi.co/api/charcters/62/","https://swapi.co/api/charcters/43/","https://swapi.co/api/charcters/11/","https://swapi.co/api/charcters/35/"], "created":"2014-12-10T15:18:20.704000Z", "edited":"2014-12-20T21:17:50.313000Z", "url":"https://swapi.co/api/people/4/", "id":4}